pvspeakerdemo/LICENSE
pvspeakerdemo/pv_speaker_demo.py
pvspeakerdemo-1.0.5.dist-info/METADATA
pvspeakerdemo-1.0.5.dist-info/WHEEL
pvspeakerdemo-1.0.5.dist-info/entry_points.txt
pvspeakerdemo-1.0.5.dist-info/top_level.txt
pvspeakerdemo-1.0.5.dist-info/RECORD
