Metadata-Version: 2.1
Name: pvspeakerdemo
Version: 1.0.5
Summary: Speaker library for Picovoice.
Home-page: https://github.com/Picovoice/pvspeaker
Author: Picovoice
Author-email: hello@picovoice.ai
Keywords: Audio Player
Classifier: Development Status :: 5 - Production/Stable
Classifier: Intended Audience :: Developers
Classifier: License :: OSI Approved :: Apache Software License
Classifier: Operating System :: OS Independent
Classifier: Programming Language :: Python :: 3
Classifier: Topic :: Multimedia :: Sound/Audio :: Speech
Requires-Python: >=3.9
Requires-Dist: pvspeaker==1.0.5
